poetry.py
poetry_chad-0.1.2.dist-info/LICENSE
poetry_chad-0.1.2.dist-info/WHEEL
poetry_chad-0.1.2.dist-info/METADATA
poetry_chad-0.1.2.dist-info/RECORD
