Metadata-Version: 2.1
Name: poetry-chad
Version: 0.1.2
Summary: Learn-by-doing python package
Author: DevonPeroutky
Author-email: devonperoutky@gmail.com
Requires-Python: >=3.9,<4.0
Classifier: Programming Language :: Python :: 3
Classifier: Programming Language :: Python :: 3.10
Classifier: Programming Language :: Python :: 3.9
